pccontext/__init__.py
pccontext/backend/__init__.py
pccontext/backend/base.py
pccontext/backend/blockfrost.py
pccontext/backend/cardano_cli.py
pccontext/backend/koios.py
pccontext/backend/kupo.py
pccontext/backend/offline_transfer_file.py
pccontext/backend/ogmios.py
pccontext/backend/yaci_devkit.py
pccontext/enums/__init__.py
pccontext/enums/address_type_enum.py
pccontext/enums/era_enum.py
pccontext/enums/history_type_enum.py
pccontext/enums/network_enum.py
pccontext/enums/transaction_type_enum.py
pccontext/exceptions.py
pccontext/logging.py
pccontext/models/__init__.py
pccontext/models/address_info_model.py
pccontext/models/base_model.py
pccontext/models/genesis_parameters_model.py
pccontext/models/offline_transfer_model.py
pccontext/models/protocol_parameters_model.py
pccontext/models/stake_address_info_model.py
pccontext/models/token_metadata_model.py
pccontext/transactions/__init__.py
pccontext/transactions/assemble.py
pccontext/transactions/explorer.py
pccontext/transactions/sign.py
pccontext/transactions/stake_address_deregistration.py
pccontext/transactions/stake_address_registration.py
pccontext/transactions/stake_address_registration_and_delegation.py
pccontext/transactions/stake_address_registration_and_vote_delegation.py
pccontext/transactions/stake_address_registration_delegation_and_vote_delegation.py
pccontext/transactions/stake_and_vote_delegation.py
pccontext/transactions/stake_delegation.py
pccontext/transactions/vote_delegation.py
pccontext/transactions/withdraw_rewards.py
pccontext/transactions/witness.py
pccontext/utils/__init__.py
pccontext/utils/file_utils.py
pccontext/utils/formatters.py
pccontext/utils/transaction_utils.py
pccontext/utils/validators.py
pccontext-0.6.0.dist-info/METADATA
pccontext-0.6.0.dist-info/WHEEL
pccontext-0.6.0.dist-info/RECORD
