Metadata-Version: 2.3
Name: pccontext
Version: 0.6.0
Summary: Chain Contexts for PyCardano library
License: MIT
Keywords: python,cardano,blockchain,crypto
Author: Hareem Adderley
Author-email: haddderley@kingpinapps.com
Requires-Python: >=3.10,<4.0
Classifier: Intended Audience :: Developers
Classifier: License :: OSI Approved :: MIT License
Classifier: Natural Language :: English
Classifier: Programming Language :: Python :: 3
Classifier: Programming Language :: Python :: 3.10
Classifier: Programming Language :: Python :: 3.11
Classifier: Programming Language :: Python :: 3.12
Classifier: Programming Language :: Python :: 3.13
Classifier: Programming Language :: Python :: 3.8
Classifier: Programming Language :: Python :: 3.9
Requires-Dist: cachetools (>=5.5.2,<6.0.0)
Requires-Dist: koios-python (>=2.0.0,<3.0.0)
Requires-Dist: ogmios (>=1.4.2,<2.0.0)
Requires-Dist: pycardano (>=0.19.0,<0.20.0)
Requires-Dist: requests (>=2.32.4,<3.0.0)
Requires-Dist: yaci-client (>=1.0,<2.0)
Project-URL: Documentation, https://pycardano.readthedocs.io/en/latest/
Project-URL: Homepage, https://github.com/Python-Cardano/pycardano
Project-URL: Repository, https://github.com/KINGH242/pccontext.git
